{
  "model": "gemma",
  "benchmark": "flickr30k_entities",
  "report": {
    "benchmark": "flickr30k_entities",
    "dataset": "flickr30k_entities",
    "num_samples": 10,
    "num_candidate_labels": 19,
    "results": [
      {
        "index": 1,
        "prompt_labels": [
          "A man",
          "a yellow helmet",
          "a cliff face",
          "snow"
        ],
        "prediction": "Sorry, as a base VLM I am not trained to answer this question.",
        "correct": false,
        "valid_labels": [
          "A man",
          "a yellow helmet",
          "a cliff face",
          "snow"
        ],
        "ground_truth_boxes": [
          {
            "label": "A man",
            "xyxy": [
              285.9569397,
              52.67939377,
              389.3494873,
              203.69972229
            ]
          },
          {
            "label": "a yellow helmet",
            "xyxy": [
              352.44180298,
              52.29131699,
              389.74865723,
              79.8338623
            ]
          },
          {
            "label": "a cliff face",
            "xyxy": [
              1.32843852,
              187.75733948,
              499.7583313,
              374.63452148
            ]
          },
          {
            "label": "snow",
            "xyxy": [
              1.56399608,
              1.82078409,
              499.49630737,
              212.78866577
            ]
          }
        ],
        "predicted_boxes": [],
        "stats": {
          "success": true,
          "error": null,
          "wall_clock_time_seconds": 36.63508199999342,
          "generation_time_seconds": 36.467119799985085,
          "first_token_latency_seconds": null,
          "time_per_output_token_seconds": 2.279194987499068,
          "output_tokens": 16,
          "retry_count": 0,
          "truncated": false,
          "peak_cpu_ram_bytes": 11914989568,
          "cpu_utilization_percent": 402.3183588317107,
          "peak_gpu_memory_bytes": null,
          "gpu_utilization_percent": null,
          "vram_allocation_over_time_bytes": null,
          "disk_offload_volume_bytes": null,
          "generated_output_count": 0,
          "hallucinated_label_count": 0,
          "false_positive_count": 0,
          "false_negative_count": 4,
          "predicted_detection_count": 0
        },
        "precision": 0.0,
        "recall": 0.0,
        "f1": 0.0,
        "tp": 0,
        "fp": 0,
        "fn": 4,
        "mean_iou_matched": 0.0,
        "mean_iou_all_predictions": 0.0,
        "matched_predictions": [],
        "matched_targets": []
      },
      {
        "index": 2,
        "prompt_labels": [
          "A dog of dark color",
          "A man",
          "A smiling woman",
          "A soccer player",
          "A woman",
          "A young person",
          "A young teenage girl",
          "a car",
          "a cliff face",
          "a hosepipe"
        ],
        "prediction": "Sorry, as a base VLM I am not trained to answer this question.",
        "correct": false,
        "valid_labels": [],
        "ground_truth_boxes": [],
        "predicted_boxes": [],
        "stats": {
          "success": true,
          "error": null,
          "wall_clock_time_seconds": 20.955973999982234,
          "generation_time_seconds": 20.79708039999241,
          "first_token_latency_seconds": null,
          "time_per_output_token_seconds": 1.2998175249995256,
          "output_tokens": 16,
          "retry_count": 0,
          "truncated": false,
          "peak_cpu_ram_bytes": 11885899776,
          "cpu_utilization_percent": 722.4717073170732,
          "peak_gpu_memory_bytes": null,
          "gpu_utilization_percent": null,
          "vram_allocation_over_time_bytes": null,
          "disk_offload_volume_bytes": null,
          "generated_output_count": 0,
          "hallucinated_label_count": 0,
          "false_positive_count": 0,
          "false_negative_count": 0,
          "predicted_detection_count": 0
        },
        "precision": 0.0,
        "recall": 0.0,
        "f1": 0.0,
        "tp": 0,
        "fp": 0,
        "fn": 0,
        "mean_iou_matched": 0.0,
        "mean_iou_all_predictions": 0.0,
        "matched_predictions": [],
        "matched_targets": []
      },
      {
        "index": 3,
        "prompt_labels": [
          "A young teenage girl",
          "a car",
          "a hosepipe"
        ],
        "prediction": "Car: [0.1, 0.2, 0.3, 0.4]\nCar: [0.1, 0",
        "correct": false,
        "valid_labels": [
          "A young teenage girl",
          "a car",
          "a hosepipe"
        ],
        "ground_truth_boxes": [
          {
            "label": "A young teenage girl",
            "xyxy": [
              24.44830513,
              27.76274109,
              362.45361328,
              374.54730225
            ]
          },
          {
            "label": "a car",
            "xyxy": [
              76.35383606,
              112.24752808,
              499.89920044,
              374.74987793
            ]
          },
          {
            "label": "a hosepipe",
            "xyxy": [
              343.10186768,
              189.2989502,
              453.77529907,
              311.07369995
            ]
          }
        ],
        "predicted_boxes": [],
        "stats": {
          "success": true,
          "error": null,
          "wall_clock_time_seconds": 25.806465100031346,
          "generation_time_seconds": 25.722616499988362,
          "first_token_latency_seconds": null,
          "time_per_output_token_seconds": 0.8038317656246363,
          "output_tokens": 32,
          "retry_count": 0,
          "truncated": true,
          "peak_cpu_ram_bytes": 11935072256,
          "cpu_utilization_percent": 790.5291338582676,
          "peak_gpu_memory_bytes": null,
          "gpu_utilization_percent": null,
          "vram_allocation_over_time_bytes": null,
          "disk_offload_volume_bytes": null,
          "generated_output_count": 1,
          "hallucinated_label_count": 1,
          "false_positive_count": 0,
          "false_negative_count": 3,
          "predicted_detection_count": 1
        },
        "precision": 0.0,
        "recall": 0.0,
        "f1": 0.0,
        "tp": 0,
        "fp": 0,
        "fn": 3,
        "mean_iou_matched": 0.0,
        "mean_iou_all_predictions": 0.0,
        "matched_predictions": [],
        "matched_targets": []
      },
      {
        "index": 4,
        "prompt_labels": [
          "A soccer player",
          "the ball"
        ],
        "prediction": "The ball is a soccer ball.",
        "correct": false,
        "valid_labels": [
          "A soccer player",
          "the ball"
        ],
        "ground_truth_boxes": [
          {
            "label": "A soccer player",
            "xyxy": [
              96.1496048,
              45.72498703,
              404.16009521,
              448.82049561
            ]
          },
          {
            "label": "the ball",
            "xyxy": [
              101.59225464,
              310.4765625,
              409.03567505,
              440.19851685
            ]
          }
        ],
        "predicted_boxes": [],
        "stats": {
          "success": true,
          "error": null,
          "wall_clock_time_seconds": 11.839552200050093,
          "generation_time_seconds": 11.819430000032298,
          "first_token_latency_seconds": null,
          "time_per_output_token_seconds": 1.6884900000046141,
          "output_tokens": 7,
          "retry_count": 0,
          "truncated": false,
          "peak_cpu_ram_bytes": 11951898624,
          "cpu_utilization_percent": 788.1995708154507,
          "peak_gpu_memory_bytes": null,
          "gpu_utilization_percent": null,
          "vram_allocation_over_time_bytes": null,
          "disk_offload_volume_bytes": null,
          "generated_output_count": 0,
          "hallucinated_label_count": 0,
          "false_positive_count": 0,
          "false_negative_count": 2,
          "predicted_detection_count": 0
        },
        "precision": 0.0,
        "recall": 0.0,
        "f1": 0.0,
        "tp": 0,
        "fp": 0,
        "fn": 2,
        "mean_iou_matched": 0.0,
        "mean_iou_all_predictions": 0.0,
        "matched_predictions": [],
        "matched_targets": []
      },
      {
        "index": 5,
        "prompt_labels": [
          "A young person",
          "a trunk of a tree"
        ],
        "prediction": "Sorry, as a base VLM I am not trained to answer this question.",
        "correct": false,
        "valid_labels": [
          "A young person",
          "a trunk of a tree"
        ],
        "ground_truth_boxes": [
          {
            "label": "A young person",
            "xyxy": [
              127.41062164,
              15.52435017,
              243.50341797,
              221.45497131
            ]
          },
          {
            "label": "a trunk of a tree",
            "xyxy": [
              225.28630066,
              1.32623792,
              499.75704956,
              320.48974609
            ]
          }
        ],
        "predicted_boxes": [],
        "stats": {
          "success": true,
          "error": null,
          "wall_clock_time_seconds": 16.907436300010886,
          "generation_time_seconds": 16.85635270003695,
          "first_token_latency_seconds": null,
          "time_per_output_token_seconds": 1.0535220437523094,
          "output_tokens": 16,
          "retry_count": 0,
          "truncated": false,
          "peak_cpu_ram_bytes": 11958513664,
          "cpu_utilization_percent": 787.2501501501501,
          "peak_gpu_memory_bytes": null,
          "gpu_utilization_percent": null,
          "vram_allocation_over_time_bytes": null,
          "disk_offload_volume_bytes": null,
          "generated_output_count": 0,
          "hallucinated_label_count": 0,
          "false_positive_count": 0,
          "false_negative_count": 2,
          "predicted_detection_count": 0
        },
        "precision": 0.0,
        "recall": 0.0,
        "f1": 0.0,
        "tp": 0,
        "fp": 0,
        "fn": 2,
        "mean_iou_matched": 0.0,
        "mean_iou_all_predictions": 0.0,
        "matched_predictions": [],
        "matched_targets": []
      },
      {
        "index": 6,
        "prompt_labels": [
          "A woman",
          "a red shirt",
          "the desk of the Ottawa Music Academy"
        ],
        "prediction": "The image is of a woman in a red shirt sitting at a desk. The desk is blue. The woman is wearing a red shirt. The image is of",
        "correct": false,
        "valid_labels": [
          "A woman",
          "a red shirt",
          "the desk of the Ottawa Music Academy"
        ],
        "ground_truth_boxes": [
          {
            "label": "A woman",
            "xyxy": [
              218.59825134,
              156.89651489,
              289.58703613,
              213.01829529
            ]
          },
          {
            "label": "a red shirt",
            "xyxy": [
              224.68873596,
              186.64181519,
              289.51785278,
              213.22612
            ]
          },
          {
            "label": "the desk of the Ottawa Music Academy",
            "xyxy": [
              14.99991131,
              204.26428223,
              462.28897095,
              374.70837402
            ]
          }
        ],
        "predicted_boxes": [],
        "stats": {
          "success": true,
          "error": null,
          "wall_clock_time_seconds": 24.825988700031303,
          "generation_time_seconds": 24.768110500008333,
          "first_token_latency_seconds": null,
          "time_per_output_token_seconds": 0.7740034531252604,
          "output_tokens": 32,
          "retry_count": 0,
          "truncated": true,
          "peak_cpu_ram_bytes": 11930132480,
          "cpu_utilization_percent": 788.1486707566462,
          "peak_gpu_memory_bytes": null,
          "gpu_utilization_percent": null,
          "vram_allocation_over_time_bytes": null,
          "disk_offload_volume_bytes": null,
          "generated_output_count": 0,
          "hallucinated_label_count": 0,
          "false_positive_count": 0,
          "false_negative_count": 3,
          "predicted_detection_count": 0
        },
        "precision": 0.0,
        "recall": 0.0,
        "f1": 0.0,
        "tp": 0,
        "fp": 0,
        "fn": 3,
        "mean_iou_matched": 0.0,
        "mean_iou_all_predictions": 0.0,
        "matched_predictions": [],
        "matched_targets": []
      },
      {
        "index": 7,
        "prompt_labels": [
          "A dog of dark color",
          "A man",
          "A smiling woman",
          "A soccer player",
          "A woman",
          "A young person",
          "A young teenage girl",
          "a car",
          "a cliff face",
          "a hosepipe"
        ],
        "prediction": "Sorry, as a base VLM I am not trained to answer this question.",
        "correct": false,
        "valid_labels": [],
        "ground_truth_boxes": [],
        "predicted_boxes": [],
        "stats": {
          "success": true,
          "error": null,
          "wall_clock_time_seconds": 17.257981900009327,
          "generation_time_seconds": 17.21961620001821,
          "first_token_latency_seconds": null,
          "time_per_output_token_seconds": 1.076226012501138,
          "output_tokens": 16,
          "retry_count": 0,
          "truncated": false,
          "peak_cpu_ram_bytes": 11952439296,
          "cpu_utilization_percent": 788.3273529411764,
          "peak_gpu_memory_bytes": null,
          "gpu_utilization_percent": null,
          "vram_allocation_over_time_bytes": null,
          "disk_offload_volume_bytes": null,
          "generated_output_count": 0,
          "hallucinated_label_count": 0,
          "false_positive_count": 0,
          "false_negative_count": 0,
          "predicted_detection_count": 0
        },
        "precision": 0.0,
        "recall": 0.0,
        "f1": 0.0,
        "tp": 0,
        "fp": 0,
        "fn": 0,
        "mean_iou_matched": 0.0,
        "mean_iou_all_predictions": 0.0,
        "matched_predictions": [],
        "matched_targets": []
      },
      {
        "index": 8,
        "prompt_labels": [
          "A dog of dark color",
          "a red leash",
          "his mouth"
        ],
        "prediction": "The image must be in the format of a single line of text.",
        "correct": false,
        "valid_labels": [
          "A dog of dark color",
          "a red leash",
          "his mouth"
        ],
        "ground_truth_boxes": [
          {
            "label": "A dog of dark color",
            "xyxy": [
              26.94587326,
              1.43705559,
              406.35650635,
              449.75827026
            ]
          },
          {
            "label": "a red leash",
            "xyxy": [
              38.22727585,
              1.35720038,
              499.50909424,
              452.29302979
            ]
          },
          {
            "label": "his mouth",
            "xyxy": [
              128.41719055,
              261.21554565,
              318.73123169,
              372.40115356
            ]
          }
        ],
        "predicted_boxes": [],
        "stats": {
          "success": true,
          "error": null,
          "wall_clock_time_seconds": 15.440490300010424,
          "generation_time_seconds": 15.381247799959965,
          "first_token_latency_seconds": null,
          "time_per_output_token_seconds": 1.0986605571399974,
          "output_tokens": 14,
          "retry_count": 0,
          "truncated": false,
          "peak_cpu_ram_bytes": 11942207488,
          "cpu_utilization_percent": 786.7911184210526,
          "peak_gpu_memory_bytes": null,
          "gpu_utilization_percent": null,
          "vram_allocation_over_time_bytes": null,
          "disk_offload_volume_bytes": null,
          "generated_output_count": 0,
          "hallucinated_label_count": 0,
          "false_positive_count": 0,
          "false_negative_count": 3,
          "predicted_detection_count": 0
        },
        "precision": 0.0,
        "recall": 0.0,
        "f1": 0.0,
        "tp": 0,
        "fp": 0,
        "fn": 3,
        "mean_iou_matched": 0.0,
        "mean_iou_all_predictions": 0.0,
        "matched_predictions": [],
        "matched_targets": []
      },
      {
        "index": 9,
        "prompt_labels": [
          "A smiling woman",
          "her right arm"
        ],
        "prediction": "A smiling woman, her right arm",
        "correct": false,
        "valid_labels": [
          "A smiling woman",
          "her right arm"
        ],
        "ground_truth_boxes": [
          {
            "label": "A smiling woman",
            "xyxy": [
              647488.0,
              647489.0,
              647491.0,
              647490.0
            ]
          },
          {
            "label": "her right arm",
            "xyxy": [
              1.0,
              2.0,
              4.0,
              3.0
            ]
          }
        ],
        "predicted_boxes": [],
        "stats": {
          "success": true,
          "error": null,
          "wall_clock_time_seconds": 11.575669200043194,
          "generation_time_seconds": 11.537032900028862,
          "first_token_latency_seconds": null,
          "time_per_output_token_seconds": 1.6481475571469804,
          "output_tokens": 7,
          "retry_count": 0,
          "truncated": false,
          "peak_cpu_ram_bytes": 11960131584,
          "cpu_utilization_percent": 788.8767543859649,
          "peak_gpu_memory_bytes": null,
          "gpu_utilization_percent": null,
          "vram_allocation_over_time_bytes": null,
          "disk_offload_volume_bytes": null,
          "generated_output_count": 0,
          "hallucinated_label_count": 0,
          "false_positive_count": 0,
          "false_negative_count": 2,
          "predicted_detection_count": 0
        },
        "precision": 0.0,
        "recall": 0.0,
        "f1": 0.0,
        "tp": 0,
        "fp": 0,
        "fn": 2,
        "mean_iou_matched": 0.0,
        "mean_iou_all_predictions": 0.0,
        "matched_predictions": [],
        "matched_targets": []
      },
      {
        "index": 10,
        "prompt_labels": [
          "A woman"
        ],
        "prediction": "0.1, 0.2, 0.3, 0.4",
        "correct": false,
        "valid_labels": [
          "A woman"
        ],
        "ground_truth_boxes": [
          {
            "label": "A woman",
            "xyxy": [
              169.04872131,
              176.33039856,
              335.65115356,
              326.91192627
            ]
          }
        ],
        "predicted_boxes": [],
        "stats": {
          "success": true,
          "error": null,
          "wall_clock_time_seconds": 17.64617530000396,
          "generation_time_seconds": 17.623090699955355,
          "first_token_latency_seconds": null,
          "time_per_output_token_seconds": 0.9790605944419641,
          "output_tokens": 18,
          "retry_count": 0,
          "truncated": false,
          "peak_cpu_ram_bytes": 11966205952,
          "cpu_utilization_percent": 788.8629310344827,
          "peak_gpu_memory_bytes": null,
          "gpu_utilization_percent": null,
          "vram_allocation_over_time_bytes": null,
          "disk_offload_volume_bytes": null,
          "generated_output_count": 0,
          "hallucinated_label_count": 0,
          "false_positive_count": 0,
          "false_negative_count": 1,
          "predicted_detection_count": 0
        },
        "precision": 0.0,
        "recall": 0.0,
        "f1": 0.0,
        "tp": 0,
        "fp": 0,
        "fn": 1,
        "mean_iou_matched": 0.0,
        "mean_iou_all_predictions": 0.0,
        "matched_predictions": [],
        "matched_targets": []
      }
    ],
    "stats": {
      "wall_clock_time_seconds": 198.96877579996362,
      "wall_clock_time_per_sample_seconds_mean": 19.88908150001662,
      "total_generation_time_seconds_mean": 19.819169750000583,
      "first_token_latency_seconds_mean": null,
      "time_per_output_token_seconds_mean": 1.2700954496235493,
      "samples_per_second": 0.05025914221864468,
      "number_of_output_tokens_mean": 17.4,
      "number_of_generated_outputs_mean": 0.1,
      "number_of_benchmark_samples_completed": 10,
      "success_count": 10,
      "failure_count": 0,
      "retry_count": 0,
      "peak_cpu_ram_bytes": 11966205952,
      "peak_gpu_memory_bytes": null,
      "cpu_utilization_percent_mean": 743.1775748511975,
      "gpu_utilization_percent_mean": null,
      "vram_allocation_over_time_bytes": null,
      "disk_offload_volume_bytes": null,
      "truncation_rate": 0.2,
      "hallucinated_label_rate": 0.1,
      "false_positive_count_total": 0,
      "false_negative_count_total": 20,
      "mean_number_of_predicted_detections": 0.1,
      "tokens_per_second": 0.8779378863738472,
      "model_load_time_seconds": 9.88233809999656
    }
  }
}